{
  "_class": "symbolMaster",
  "backgroundColor": {
    "_class": "color",
    "alpha": 1,
    "blue": 1,
    "do_objectID": "70A7E64B-274A-444C-8A00-C33A0F5C4366",
    "green": 1,
    "red": 1
  },
  "booleanOperation": 0,
  "changeIdentifier": 441,
  "clippingMaskMode": 0,
  "do_objectID": "8FF5A135-4F84-48FB-8CF8-E4BD4F1AEF42",
  "exportOptions": {
    "_class": "exportOptions",
    "do_objectID": "71D964B0-5EE0-4960-B9E0-8590E0C9D057",
    "exportFormats": [
    ],
    "includedLayerIds": [
    ],
    "layerOptions": 0,
    "shouldTrim": false
  },
  "frame": {
    "_class": "rect",
    "constrainProportions": false,
    "do_objectID": "5043BB34-3387-495F-801D-7A899C7AE74D",
    "height": 217,
    "width": 386,
    "x": 8997,
    "y": 7620
  },
  "groupLayout": {
    "_class": "MSImmutableFreeformGroupLayout"
  },
  "hasBackgroundColor": false,
  "hasClickThrough": true,
  "hasClippingMask": false,
  "horizontalRulerData": {
    "_class": "rulerData",
    "base": 0,
    "do_objectID": "F3D5675C-38E0-4BD9-9250-7F09E257ABC4",
    "guides": [
    ]
  },
  "includeBackgroundColorInExport": true,
  "includeBackgroundColorInInstance": true,
  "includeInCloudUpload": true,
  "isFixedToViewport": false,
  "isFlippedHorizontal": false,
  "isFlippedVertical": false,
  "isFlowHome": false,
  "isLocked": false,
  "isVisible": true,
  "layerListExpandedType": 2,
  "layers": [
    {
      "class": "group",
      "id": "AEF292A5-D55E-4D4A-892C-C873FCC84899"
    }
  ],
  "name": "Timeline / WeiboCard / 414 /Ask&Answer",
  "nameIsFixed": true,
  "overrideProperties": [
    {
      "_class": "MSImmutableOverrideProperty",
      "canOverride": true,
      "overrideName": "E1215F99-5B8D-4D31-ABC7-7DC4C4BB5D88_stringValue"
    },
    {
      "_class": "MSImmutableOverrideProperty",
      "canOverride": true,
      "overrideName": "8BC689DF-5E55-4E49-8399-C5EB86360460_stringValue"
    },
    {
      "_class": "MSImmutableOverrideProperty",
      "canOverride": true,
      "overrideName": "788CA6A9-D5A3-48E9-A37A-4AFFC94CCCBA_stringValue"
    },
    {
      "_class": "MSImmutableOverrideProperty",
      "canOverride": true,
      "overrideName": "788CA6A9-D5A3-48E9-A37A-4AFFC94CCCBA_textStyle"
    },
    {
      "_class": "MSImmutableOverrideProperty",
      "canOverride": true,
      "overrideName": "D1CCA121-5752-4CD8-AA4D-4332EB33EE10_stringValue"
    },
    {
      "_class": "MSImmutableOverrideProperty",
      "canOverride": true,
      "overrideName": "5E46D477-2947-4153-9AE4-CEC1F59B13D7_stringValue"
    },
    {
      "_class": "MSImmutableOverrideProperty",
      "canOverride": true,
      "overrideName": "F6DCE0B4-2F35-4F11-87D0-37DE5DFE90CF_stringValue"
    }
  ],
  "resizesContent": false,
  "resizingConstraint": 63,
  "resizingType": 0,
  "rotation": 0,
  "shouldBreakMaskChain": true,
  "style": {
    "_class": "style",
    "do_objectID": "77A895E5-8821-4716-BE28-1B15116003D1",
    "endMarkerType": 0,
    "miterLimit": 10,
    "startMarkerType": 0,
    "windingRule": 1
  },
  "symbolID": "6CE4CAE4-2B28-472D-A928-3355230FFB10",
  "verticalRulerData": {
    "_class": "rulerData",
    "base": 0,
    "do_objectID": "9B8A3327-D27A-4676-92B2-C03C5E128802",
    "guides": [
    ]
  }
}