{
  "_class": "slice",
  "backgroundColor": {
    "_class": "color",
    "alpha": 1,
    "blue": 1,
    "do_objectID": "5FCCD66C-52E3-4A4A-94B2-A8871B457CB3",
    "green": 1,
    "red": 1
  },
  "booleanOperation": 0,
  "do_objectID": "F9AFBBC2-3C27-4889-8886-BACDEB629677",
  "exportOptions": {
    "_class": "exportOptions",
    "do_objectID": "20871128-9ADE-49A3-B99C-E5834F624F19",
    "exportFormats": [
      {
        "_class": "exportFormat",
        "absoluteSize": 0,
        "fileFormat": "png",
        "name": "",
        "namingScheme": 0,
        "scale": 1,
        "visibleScaleType": 0
      }
    ],
    "includedLayerIds": [
    ],
    "layerOptions": 0,
    "shouldTrim": false
  },
  "frame": {
    "_class": "rect",
    "constrainProportions": false,
    "do_objectID": "186A616A-61D9-4233-93D7-52364E7749A3",
    "height": 60,
    "width": 60,
    "x": 783,
    "y": 2357
  },
  "hasBackgroundColor": false,
  "isFixedToViewport": false,
  "isFlippedHorizontal": false,
  "isFlippedVertical": false,
  "isLocked": false,
  "isVisible": true,
  "layerListExpandedType": 0,
  "name": "half_compose_icon_keyboard@3x",
  "nameIsFixed": true,
  "resizingConstraint": 63,
  "resizingType": 0,
  "rotation": 0,
  "shouldBreakMaskChain": false
}