{
  "_class": "symbolInstance",
  "booleanOperation": 0,
  "do_objectID": "BCCF3ADD-ACCA-47F7-B9D6-85EB61B13D65",
  "exportOptions": {
    "_class": "exportOptions",
    "do_objectID": "498BEC4C-0259-4A5F-936F-43CBC7CF12CC",
    "exportFormats": [
    ],
    "includedLayerIds": [
    ],
    "layerOptions": 0,
    "shouldTrim": false
  },
  "frame": {
    "_class": "rect",
    "constrainProportions": true,
    "do_objectID": "4835C906-DEE9-456C-A8A2-1C5FB0F60D41",
    "height": 28,
    "width": 313,
    "x": 0,
    "y": 0
  },
  "horizontalSpacing": 0,
  "isFixedToViewport": false,
  "isFlippedHorizontal": false,
  "isFlippedVertical": false,
  "isLocked": false,
  "isVisible": true,
  "layerListExpandedType": 0,
  "name": "TextField / SearchBar / Gray",
  "nameIsFixed": false,
  "overrideValues": [
  ],
  "resizingConstraint": 63,
  "resizingType": 0,
  "rotation": 0,
  "scale": 1,
  "shouldBreakMaskChain": false,
  "style": {
    "_class": "style",
    "blur": {
      "_class": "blur",
      "center": "{0.5, 0.5}",
      "do_objectID": "25C7D8CB-1D31-454A-B3F2-39BFFC7619D5",
      "isEnabled": false,
      "motionAngle": 0,
      "radius": 5,
      "type": 0
    },
    "do_objectID": "068B9679-BB6E-4FE4-9FEB-02AE0BEBE634",
    "endMarkerType": 0,
    "miterLimit": 10,
    "startMarkerType": 0,
    "windingRule": 1
  },
  "symbolID": "AC388CEC-DCFE-4959-8FDF-F11AD224ACEA",
  "verticalSpacing": 0
}