{
  "_class": "symbolInstance",
  "booleanOperation": 0,
  "clippingMaskMode": 0,
  "do_objectID": "9A32FC55-3FCF-4890-8A75-1D62734072EA",
  "exportOptions": {
    "_class": "exportOptions",
    "do_objectID": "C15F56EA-B276-43C2-BECC-CDB9B90C2CD4",
    "exportFormats": [
    ],
    "includedLayerIds": [
    ],
    "layerOptions": 0,
    "shouldTrim": false
  },
  "frame": {
    "_class": "rect",
    "constrainProportions": false,
    "do_objectID": "24CAAC4D-760E-4BA9-A8AD-D17C414733D5",
    "height": 88,
    "width": 414,
    "x": 0,
    "y": 0
  },
  "hasClippingMask": false,
  "horizontalSpacing": 0,
  "isFixedToViewport": false,
  "isFlippedHorizontal": false,
  "isFlippedVertical": false,
  "isLocked": false,
  "isVisible": true,
  "layerListExpandedType": 0,
  "name": "Background",
  "nameIsFixed": true,
  "overrideValues": [
  ],
  "resizingConstraint": 18,
  "resizingType": 0,
  "rotation": 0,
  "scale": 1,
  "shouldBreakMaskChain": false,
  "style": {
    "_class": "style",
    "blur": {
      "_class": "blur",
      "center": "{0.5, 0.5}",
      "do_objectID": "DB8FF42B-217A-461E-A347-A82E4500A3F8",
      "isEnabled": false,
      "motionAngle": 0,
      "radius": 5,
      "saturation": 1,
      "type": 0
    },
    "do_objectID": "1BE7F0E2-61DF-40AF-97E9-5570CE8D9EBB",
    "endMarkerType": 0,
    "miterLimit": 10,
    "startMarkerType": 0,
    "windingRule": 1
  },
  "symbolID": "5BE6B964-7E16-40BE-852E-D1B18628A5C4",
  "verticalSpacing": 0
}