{
  "_class": "symbolInstance",
  "booleanOperation": 0,
  "do_objectID": "70FD58AC-05E6-4603-8E39-2990044D247B",
  "exportOptions": {
    "_class": "exportOptions",
    "do_objectID": "C4F8E8B6-3B0C-4797-8605-619D6EBA6A5F",
    "exportFormats": [
    ],
    "includedLayerIds": [
    ],
    "layerOptions": 0,
    "shouldTrim": false
  },
  "frame": {
    "_class": "rect",
    "constrainProportions": false,
    "do_objectID": "2BAC4EC7-331E-4D0C-BF9D-9641E503D8D8",
    "height": 134,
    "width": 269.9999999999999,
    "x": 53,
    "y": 267
  },
  "horizontalSpacing": 0,
  "isFixedToViewport": false,
  "isFlippedHorizontal": false,
  "isFlippedVertical": false,
  "isLocked": false,
  "isVisible": true,
  "layerListExpandedType": 0,
  "name": "Dialog / Title",
  "nameIsFixed": false,
  "overrideValues": [
    {
      "_class": "overrideValue",
      "overrideName": "3734D392-7A4D-44CC-8D2D-79A9232BCD7D_symbolID",
      "value": "54AA2247-0F0A-4B32-9F6A-E13DE97ED5AA"
    }
  ],
  "resizingConstraint": 63,
  "resizingType": 0,
  "rotation": 0,
  "scale": 1,
  "shouldBreakMaskChain": false,
  "style": {
    "_class": "style",
    "do_objectID": "ABC146AD-43A5-486F-8E93-A79E8E28F966",
    "endMarkerType": 0,
    "miterLimit": 10,
    "startMarkerType": 0,
    "windingRule": 1
  },
  "symbolID": "6B030764-D45C-47B0-BCD5-1C79846BB288",
  "verticalSpacing": 0
}