{
  "_class": "symbolMaster",
  "backgroundColor": {
    "_class": "color",
    "alpha": 1,
    "blue": 1,
    "do_objectID": "5C0FF99B-5BDA-4958-BCEA-908AFEE9092B",
    "green": 1,
    "red": 1
  },
  "booleanOperation": 0,
  "changeIdentifier": 1829,
  "clippingMaskMode": 0,
  "do_objectID": "CFDF24C2-8D00-43DE-A75F-11C4C3A6AAB9",
  "exportOptions": {
    "_class": "exportOptions",
    "do_objectID": "B2098E7D-073B-43DF-9C78-0708BCD53BE8",
    "exportFormats": [
    ],
    "includedLayerIds": [
    ],
    "layerOptions": 0,
    "shouldTrim": false
  },
  "frame": {
    "_class": "rect",
    "constrainProportions": false,
    "do_objectID": "732D79C6-E409-4F2B-9C7A-8409B73233A9",
    "height": 258,
    "width": 349,
    "x": 7947,
    "y": 10311
  },
  "groupLayout": {
    "_class": "MSImmutableFreeformGroupLayout"
  },
  "hasBackgroundColor": false,
  "hasClickThrough": true,
  "hasClippingMask": false,
  "horizontalRulerData": {
    "_class": "rulerData",
    "base": 0,
    "do_objectID": "DFBF97A9-4842-456C-B944-0DE661AA47EF",
    "guides": [
    ]
  },
  "includeBackgroundColorInExport": true,
  "includeBackgroundColorInInstance": false,
  "includeInCloudUpload": true,
  "isFixedToViewport": false,
  "isFlippedHorizontal": false,
  "isFlippedVertical": false,
  "isFlowHome": false,
  "isLocked": false,
  "isVisible": true,
  "layerListExpandedType": 2,
  "layers": [
    {
      "class": "group",
      "id": "72B278BF-C8A5-4A44-A667-732572D36782"
    }
  ],
  "name": "Timeline / WeiboCard / Small Page / AD Pic 1+2",
  "nameIsFixed": true,
  "overrideProperties": [
    {
      "_class": "MSImmutableOverrideProperty",
      "canOverride": true,
      "overrideName": "CC9D1021-B0A3-4B7C-895E-1FD07BD4FD4A_stringValue"
    },
    {
      "_class": "MSImmutableOverrideProperty",
      "canOverride": true,
      "overrideName": "025E3CE1-86EC-4FBB-B5F6-C452A21FEB60_symbolID"
    },
    {
      "_class": "MSImmutableOverrideProperty",
      "canOverride": true,
      "overrideName": "4E8D6CEC-A06F-4761-B62D-8B22DEAEAC72_stringValue"
    },
    {
      "_class": "MSImmutableOverrideProperty",
      "canOverride": true,
      "overrideName": "866CFEE4-78E8-4F61-BCFC-A1A60A45DF1F_stringValue"
    }
  ],
  "resizesContent": false,
  "resizingConstraint": 63,
  "resizingType": 0,
  "rotation": 0,
  "shouldBreakMaskChain": true,
  "style": {
    "_class": "style",
    "do_objectID": "5DFB8B3E-2D25-4AF2-922A-C6277D10314D",
    "endMarkerType": 0,
    "miterLimit": 10,
    "startMarkerType": 0,
    "windingRule": 1
  },
  "symbolID": "4CEF6C4E-66AC-42A2-B765-CD51F76889FB",
  "verticalRulerData": {
    "_class": "rulerData",
    "base": 0,
    "do_objectID": "4D077336-FB3F-4F51-AAD7-E494D91C8A08",
    "guides": [
    ]
  }
}