{
  "_class": "group",
  "booleanOperation": 0,
  "clippingMaskMode": 0,
  "do_objectID": "57CB2A00-2FC9-4811-BB9B-ABDF8BE5E443",
  "exportOptions": {
    "_class": "exportOptions",
    "do_objectID": "C4ABF435-B275-410B-8EEC-90C6FDEDE1F5",
    "exportFormats": [
    ],
    "includedLayerIds": [
    ],
    "layerOptions": 0,
    "shouldTrim": false
  },
  "frame": {
    "_class": "rect",
    "constrainProportions": false,
    "do_objectID": "0D43FD4D-B69E-4E4A-9C02-3C54337CA076",
    "height": 84,
    "width": 84,
    "x": 2491,
    "y": 2177
  },
  "hasClickThrough": false,
  "hasClippingMask": false,
  "isFixedToViewport": false,
  "isFlippedHorizontal": false,
  "isFlippedVertical": false,
  "isLocked": false,
  "isVisible": true,
  "layerListExpandedType": 1,
  "layers": [
    {
      "class": "shapePath",
      "id": "CD087E50-CD80-4663-B27A-F4D525EC1E12"
    },
    {
      "class": "slice",
      "id": "53A4D8B6-32CA-4EC1-90EA-EBF03B11711C"
    }
  ],
  "name": "toolbar_refresh_highlighted@3x",
  "nameIsFixed": true,
  "resizingConstraint": 63,
  "resizingType": 0,
  "rotation": 0,
  "shouldBreakMaskChain": false,
  "style": {
    "_class": "style",
    "blur": {
      "_class": "blur",
      "center": "{0.5, 0.5}",
      "do_objectID": "39D7C98B-59FA-4A69-8B6A-332539E4461A",
      "isEnabled": false,
      "motionAngle": 0,
      "radius": 15,
      "saturation": 1,
      "type": 0
    },
    "do_objectID": "0FBBAB76-654F-467D-9B6F-4B43E8541F05",
    "endMarkerType": 0,
    "miterLimit": 10,
    "startMarkerType": 0,
    "windingRule": 1
  }
}