{
  "_class": "symbolInstance",
  "booleanOperation": 0,
  "do_objectID": "E081B156-598A-4706-A40A-0CAF0E4D3959",
  "exportOptions": {
    "_class": "exportOptions",
    "do_objectID": "A27785CD-F395-4128-AAAA-3168EC652E8E",
    "exportFormats": [
    ],
    "includedLayerIds": [
    ],
    "layerOptions": 0,
    "shouldTrim": false
  },
  "frame": {
    "_class": "rect",
    "constrainProportions": false,
    "do_objectID": "8845CA9A-FB8D-4992-B2A9-35F052F41105",
    "height": 28,
    "width": 70,
    "x": 308,
    "y": 144
  },
  "horizontalSpacing": 0,
  "isFixedToViewport": false,
  "isFlippedHorizontal": false,
  "isFlippedVertical": false,
  "isLocked": false,
  "isVisible": true,
  "layerListExpandedType": 0,
  "name": "Common / Button / Small / Orange / Disable",
  "nameIsFixed": false,
  "overrideValues": [
  ],
  "resizingConstraint": 63,
  "resizingType": 0,
  "rotation": 0,
  "scale": 1,
  "shouldBreakMaskChain": false,
  "style": {
    "_class": "style",
    "do_objectID": "276FDB45-55EA-46A6-80BF-0BB5C1ED6607",
    "endMarkerType": 0,
    "miterLimit": 10,
    "startMarkerType": 0,
    "windingRule": 1
  },
  "symbolID": "2E4AC966-CB28-40FB-9193-4AD5E903696F",
  "userInfo": {
    "com.animaapp.stc-sketch-plugin": {
      "kModelPropertiesKey": {
      }
    }
  },
  "verticalSpacing": 0
}