{
  "_class": "group",
  "booleanOperation": 0,
  "do_objectID": "2C15811B-88DC-4E10-9CFB-9082BB5A4D8D",
  "exportOptions": {
    "_class": "exportOptions",
    "do_objectID": "E0A23CEB-2F51-4E2C-B81F-5A01DED2672D",
    "exportFormats": [
    ],
    "includedLayerIds": [
    ],
    "layerOptions": 0,
    "shouldTrim": false
  },
  "frame": {
    "_class": "rect",
    "constrainProportions": false,
    "do_objectID": "FA40252E-D9D5-43D8-BA1E-BDF3C4E5040D",
    "height": 184,
    "width": 1028,
    "x": 70,
    "y": 1970
  },
  "hasClickThrough": false,
  "isFixedToViewport": false,
  "isFlippedHorizontal": false,
  "isFlippedVertical": false,
  "isLocked": false,
  "isVisible": true,
  "layerListExpandedType": 1,
  "layers": [
    {
      "class": "symbolInstance",
      "id": "1AC4B12C-8B0A-41CF-97AA-A7B39884915B"
    },
    {
      "class": "symbolInstance",
      "id": "04A71927-520A-4CBA-8C28-76D2CBEE639B"
    },
    {
      "class": "symbolInstance",
      "id": "EFAE7DF2-B8C5-434B-AE81-6A0823D8A53E"
    },
    {
      "class": "symbolInstance",
      "id": "266C787F-648D-4690-B0B7-9F46F5CA2F1C"
    },
    {
      "class": "symbolInstance",
      "id": "9DCF776B-5759-4F5B-897A-6F415F00530A"
    },
    {
      "class": "symbolInstance",
      "id": "B20194A5-6047-49D3-9590-B4CFC31E201F"
    },
    {
      "class": "symbolInstance",
      "id": "2826B600-B370-46AD-B9DA-95480488A26D"
    },
    {
      "class": "symbolInstance",
      "id": "05315FA6-6DA9-4DCE-8239-091E823495F7"
    },
    {
      "class": "symbolInstance",
      "id": "5BD5E82B-BACB-4762-850C-9CB86E2691E7"
    },
    {
      "class": "symbolInstance",
      "id": "6BC3FD17-D4D6-45B2-8EB7-F5DED03EF741"
    },
    {
      "class": "symbolInstance",
      "id": "B59F7F90-7796-41E6-9C8B-0DE4268D7584"
    },
    {
      "class": "symbolInstance",
      "id": "F927FEA1-B52A-4F94-91D8-2BE24DBD6855"
    },
    {
      "class": "symbolInstance",
      "id": "F2ECB64C-16A8-42E8-AC60-0BF80E193B73"
    },
    {
      "class": "symbolInstance",
      "id": "ED1A87D3-A891-4DB8-9D5F-6DCCE597F2AE"
    },
    {
      "class": "symbolInstance",
      "id": "3A9575FB-C86F-4548-B7A0-B262B95FC5DA"
    }
  ],
  "name": "Red",
  "nameIsFixed": true,
  "resizingConstraint": 63,
  "resizingType": 0,
  "rotation": 0,
  "shouldBreakMaskChain": false,
  "style": {
    "_class": "style",
    "do_objectID": "ACC3EE33-339C-45F5-BC68-4D720CFE4FF1",
    "endMarkerType": 0,
    "miterLimit": 10,
    "startMarkerType": 0,
    "windingRule": 1
  },
  "userInfo": {
    "com.animaapp.stc-sketch-plugin": {
      "kModelPropertiesKey": {
      }
    }
  }
}