{
  "_class": "group",
  "booleanOperation": 0,
  "clippingMaskMode": 0,
  "do_objectID": "87B930C5-3F20-42C5-96DA-6749074C4846",
  "exportOptions": {
    "_class": "exportOptions",
    "do_objectID": "0EE92CAA-C017-45BC-A945-5A7964A3AED9",
    "exportFormats": [
    ],
    "includedLayerIds": [
    ],
    "layerOptions": 0,
    "shouldTrim": false
  },
  "frame": {
    "_class": "rect",
    "constrainProportions": false,
    "do_objectID": "D35B64E0-4624-40B5-9B00-DE8976D627A4",
    "height": 218,
    "width": 215,
    "x": 43.5,
    "y": 40.5
  },
  "hasClickThrough": false,
  "hasClippingMask": false,
  "isFixedToViewport": false,
  "isFlippedHorizontal": false,
  "isFlippedVertical": false,
  "isLocked": false,
  "isVisible": true,
  "layerListExpandedType": 0,
  "layers": [
    {
      "class": "shapeGroup",
      "id": "596E8732-3581-4769-A74F-E9274D0C75FC"
    },
    {
      "class": "shapeGroup",
      "id": "B05A568C-B728-470C-9639-950C8DC2E6EC"
    },
    {
      "class": "shapeGroup",
      "id": "34D24C33-C9AB-4C4C-8DA8-DD67805A2315"
    }
  ],
  "name": "empty_messages",
  "nameIsFixed": true,
  "resizingConstraint": 63,
  "resizingType": 0,
  "rotation": 0,
  "shouldBreakMaskChain": false,
  "style": {
    "_class": "style",
    "blur": {
      "_class": "blur",
      "center": "{0.5, 0.5}",
      "do_objectID": "274EF90E-84B6-4D69-A326-AF098E7E4488",
      "isEnabled": false,
      "motionAngle": 0,
      "radius": 15,
      "saturation": 1,
      "type": 0
    },
    "do_objectID": "3A75A1D1-B7C0-4EEC-8B2C-4D2A15B281DD",
    "endMarkerType": 0,
    "fills": [
      {
        "_class": "fill",
        "color": {
          "_class": "color",
          "alpha": 1,
          "blue": 0,
          "green": 0,
          "red": 0
        },
        "fillType": 0,
        "isEnabled": true,
        "noiseIndex": 0,
        "noiseIntensity": 0,
        "patternFillType": 1,
        "patternTileScale": 1
      }
    ],
    "miterLimit": 10,
    "startMarkerType": 0,
    "windingRule": 1
  }
}