{
  "_class": "group",
  "booleanOperation": 0,
  "clippingMaskMode": 0,
  "do_objectID": "08969DA5-98B7-4E10-83BE-81A01EACC7ED",
  "exportOptions": {
    "_class": "exportOptions",
    "do_objectID": "2CB5EB3B-DB0C-4944-8196-013D2DA5DE87",
    "exportFormats": [
    ],
    "includedLayerIds": [
    ],
    "layerOptions": 0,
    "shouldTrim": false
  },
  "frame": {
    "_class": "rect",
    "constrainProportions": false,
    "do_objectID": "E0A6A506-965D-4CC4-8734-79F4686BF056",
    "height": 14,
    "width": 14,
    "x": 40,
    "y": 42
  },
  "groupLayout": {
    "_class": "MSImmutableFreeformGroupLayout"
  },
  "hasClickThrough": false,
  "hasClippingMask": false,
  "isFixedToViewport": false,
  "isFlippedHorizontal": false,
  "isFlippedVertical": false,
  "isLocked": false,
  "isVisible": true,
  "layerListExpandedType": 0,
  "layers": [
    {
      "class": "rectangle",
      "id": "F97081E8-67F2-45B8-875B-427A234950A6"
    },
    {
      "class": "group",
      "id": "E0C16AF3-F0A2-44EB-8F0E-2070FDE93449"
    }
  ],
  "name": "Avatar / Icon / Vip",
  "nameIsFixed": false,
  "resizingConstraint": 63,
  "resizingType": 0,
  "rotation": 0,
  "shouldBreakMaskChain": false,
  "style": {
    "_class": "style",
    "do_objectID": "7BA90EE0-C155-45CD-A552-1A69AE80BB2D",
    "endMarkerType": 0,
    "miterLimit": 10,
    "startMarkerType": 0,
    "windingRule": 1
  }
}