{
  "_class": "symbolInstance",
  "booleanOperation": 0,
  "clippingMaskMode": 0,
  "do_objectID": "B341EA04-A39C-4C9F-A020-DD20ADAA915A",
  "exportOptions": {
    "_class": "exportOptions",
    "do_objectID": "365AB37E-29B7-4318-9087-5C9E115A8E73",
    "exportFormats": [
    ],
    "includedLayerIds": [
    ],
    "layerOptions": 0,
    "shouldTrim": false
  },
  "frame": {
    "_class": "rect",
    "constrainProportions": false,
    "do_objectID": "E9FB5DB5-28DC-4EDF-B2B5-C7C2120890C9",
    "height": 25,
    "width": 26,
    "x": 176,
    "y": 121
  },
  "hasClippingMask": false,
  "horizontalSpacing": 0,
  "isFixedToViewport": false,
  "isFlippedHorizontal": false,
  "isFlippedVertical": false,
  "isLocked": false,
  "isVisible": true,
  "layerListExpandedType": 0,
  "name": "Compose / Rate / Icon / Stars / Empty Copy 2",
  "nameIsFixed": false,
  "overrideValues": [
  ],
  "resizingConstraint": 63,
  "resizingType": 0,
  "rotation": 0,
  "scale": 1,
  "shouldBreakMaskChain": false,
  "style": {
    "_class": "style",
    "do_objectID": "B5BC7013-54C0-4FFE-9619-193AF5E3D037",
    "endMarkerType": 0,
    "miterLimit": 10,
    "startMarkerType": 0,
    "windingRule": 1
  },
  "symbolID": "B48E6E52-0FBB-45BF-97B0-96E3C97B7F55",
  "verticalSpacing": 0
}