{
  "_class": "symbolMaster",
  "allowsOverrides": true,
  "backgroundColor": {
    "_class": "color",
    "alpha": 1,
    "blue": 0.2313725490196079,
    "do_objectID": "6B0FEE8D-BD77-4AD5-A712-23C3BE44FBF4",
    "green": 0.2313725490196079,
    "red": 0.2313725490196079
  },
  "booleanOperation": 0,
  "changeIdentifier": 470,
  "clippingMaskMode": 0,
  "do_objectID": "CBFD8BD8-022A-4D77-A331-50FC5CCA488B",
  "exportOptions": {
    "_class": "exportOptions",
    "do_objectID": "55262EFD-8D5B-4BBF-B63B-A422474F3A6C",
    "exportFormats": [
    ],
    "includedLayerIds": [
    ],
    "layerOptions": 0,
    "shouldTrim": false
  },
  "frame": {
    "_class": "rect",
    "constrainProportions": false,
    "do_objectID": "442D6243-6477-4CC8-9A37-507224509A22",
    "height": 60,
    "width": 60,
    "x": 5927,
    "y": 880
  },
  "groupLayout": {
    "_class": "MSImmutableFreeformGroupLayout"
  },
  "hasBackgroundColor": false,
  "hasClickThrough": true,
  "hasClippingMask": false,
  "horizontalRulerData": {
    "_class": "rulerData",
    "base": 0,
    "do_objectID": "38F301F1-EAF2-4C2F-9DA9-52430B30E880",
    "guides": [
    ]
  },
  "includeBackgroundColorInExport": true,
  "includeBackgroundColorInInstance": false,
  "includeInCloudUpload": true,
  "isFixedToViewport": false,
  "isFlippedHorizontal": false,
  "isFlippedVertical": false,
  "isFlowHome": false,
  "isLocked": false,
  "isVisible": true,
  "layerListExpandedType": 0,
  "layers": [
    {
      "class": "oval",
      "id": "ABB9E5E0-37D5-404E-8538-6EF4510DB9B2"
    },
    {
      "class": "group",
      "id": "C909CFDE-55C9-4C0A-B678-192C5359767E"
    }
  ],
  "name": "Compose / Entrance / Icon / Comment",
  "nameIsFixed": true,
  "overrideProperties": [
  ],
  "resizesContent": false,
  "resizingConstraint": 63,
  "resizingType": 0,
  "rotation": 0,
  "shouldBreakMaskChain": true,
  "style": {
    "_class": "style",
    "blur": {
      "_class": "blur",
      "center": "{0.5, 0.5}",
      "do_objectID": "508EDB0B-1A04-4AF1-8AA4-0731750433BC",
      "isEnabled": false,
      "motionAngle": 0,
      "radius": 5,
      "saturation": 1,
      "type": 0
    },
    "do_objectID": "ADD99FF1-75D7-4B95-A59C-0AAFCB360473",
    "endMarkerType": 0,
    "fills": [
      {
        "_class": "fill",
        "color": {
          "_class": "color",
          "alpha": 1,
          "blue": 1,
          "green": 1,
          "red": 1
        },
        "fillType": 0,
        "isEnabled": true,
        "noiseIndex": 0,
        "noiseIntensity": 0,
        "patternFillType": 1,
        "patternTileScale": 1
      }
    ],
    "miterLimit": 10,
    "startMarkerType": 0,
    "windingRule": 1
  },
  "symbolID": "9BD6D3F2-CE15-40EF-B70E-61FB3618592D",
  "verticalRulerData": {
    "_class": "rulerData",
    "base": 0,
    "do_objectID": "24A0B35F-119E-457F-BEAD-A0CB59380F5F",
    "guides": [
    ]
  }
}