{
  "_class": "symbolInstance",
  "booleanOperation": 0,
  "do_objectID": "FB32A5E9-2D18-4C9E-B03E-15BB2B32A986",
  "exportOptions": {
    "_class": "exportOptions",
    "do_objectID": "D414B516-6762-431F-8A06-BF4EFE422560",
    "exportFormats": [
    ],
    "includedLayerIds": [
    ],
    "layerOptions": 0,
    "shouldTrim": false
  },
  "frame": {
    "_class": "rect",
    "constrainProportions": false,
    "do_objectID": "8F78D0B1-7D1C-421C-9172-F5325EE4B1AF",
    "height": 14,
    "width": 14,
    "x": 246,
    "y": 1972
  },
  "horizontalSpacing": 0,
  "isFixedToViewport": false,
  "isFlippedHorizontal": false,
  "isFlippedVertical": false,
  "isLocked": false,
  "isVisible": true,
  "layerListExpandedType": 0,
  "name": "Avatar / Icon / Vip",
  "nameIsFixed": false,
  "overrideValues": [
  ],
  "resizingConstraint": 63,
  "resizingType": 0,
  "rotation": 0,
  "scale": 1,
  "shouldBreakMaskChain": false,
  "style": {
    "_class": "style",
    "do_objectID": "8C6C26F2-CF92-48FD-89FB-DDF5E6A0D212",
    "endMarkerType": 0,
    "miterLimit": 10,
    "startMarkerType": 0,
    "windingRule": 1
  },
  "symbolID": "F4F7CAAB-4770-45DD-82A3-67B8F39ABD6C",
  "verticalSpacing": 0
}