{
  "_class": "symbolInstance",
  "booleanOperation": 0,
  "do_objectID": "BBA5CCCE-735A-4C69-8424-605F70D9433F",
  "exportOptions": {
    "_class": "exportOptions",
    "do_objectID": "DD8CB4F0-C10E-4DE2-BF44-4CBDBD9082B2",
    "exportFormats": [
    ],
    "includedLayerIds": [
    ],
    "layerOptions": 0,
    "shouldTrim": false
  },
  "frame": {
    "_class": "rect",
    "constrainProportions": false,
    "do_objectID": "B938446A-B3DA-403B-ACBC-ACC5D0B318FD",
    "height": 34,
    "width": 375,
    "x": 0,
    "y": 44
  },
  "horizontalSpacing": 0,
  "isFixedToViewport": false,
  "isFlippedHorizontal": false,
  "isFlippedVertical": false,
  "isLocked": false,
  "isVisible": true,
  "layerListExpandedType": 0,
  "name": "Bars/Home Indicator/Home Indicator - On Dark",
  "nameIsFixed": false,
  "overrideValues": [
  ],
  "resizingConstraint": 63,
  "resizingType": 0,
  "rotation": 0,
  "scale": 1,
  "shouldBreakMaskChain": false,
  "style": {
    "_class": "style",
    "do_objectID": "9C9775ED-6DF7-4C7D-B6E4-C1A071731426",
    "endMarkerType": 0,
    "miterLimit": 10,
    "startMarkerType": 0,
    "windingRule": 1
  },
  "symbolID": "1266D473-CA80-4BA2-8338-A64E7F3CDFE5",
  "verticalSpacing": 0
}