{
  "_class": "text",
  "attributedString": {
    "_class": "attributedString",
    "attributes": [
      {
        "_class": "stringAttribute",
        "attributes": {
          "MSAttributedStringColorAttribute": {
            "_class": "color",
            "alpha": 1,
            "blue": 0.3882352941,
            "green": 0.3882352941,
            "red": 0.3882352941
          },
          "MSAttributedStringFontAttribute": {
            "_class": "fontDescriptor",
            "attributes": {
              "name": "SFUIText-Regular",
              "size": 12
            }
          },
          "paragraphStyle": {
            "_class": "paragraphStyle",
            "alignment": 0,
            "allowsDefaultTighteningForTruncation": 0
          }
        },
        "length": 17,
        "location": 0
      }
    ],
    "string": "SubtitleText63-12"
  },
  "automaticallyDrawOnUnderlyingPath": false,
  "booleanOperation": 0,
  "clippingMaskMode": 0,
  "do_objectID": "8DD684ED-2E92-4C57-954A-9AB98ADB359C",
  "dontSynchroniseWithSymbol": false,
  "exportOptions": {
    "_class": "exportOptions",
    "do_objectID": "6B1A92ED-0A0E-4403-9CC4-58447F695DCE",
    "exportFormats": [
    ],
    "includedLayerIds": [
    ],
    "layerOptions": 0,
    "shouldTrim": false
  },
  "frame": {
    "_class": "rect",
    "constrainProportions": false,
    "do_objectID": "B002E255-8E4D-47B8-B542-63F40CD1CAEC",
    "height": 14,
    "width": 101,
    "x": 381,
    "y": 52.04549431321084
  },
  "glyphBounds": "{{0, 0}, {100, 12}}",
  "hasClippingMask": false,
  "isFixedToViewport": false,
  "isFlippedHorizontal": false,
  "isFlippedVertical": false,
  "isLocked": false,
  "isVisible": true,
  "layerListExpandedType": 0,
  "lineSpacingBehaviour": 2,
  "name": "63-12 / EN",
  "nameIsFixed": true,
  "resizingConstraint": 63,
  "resizingType": 0,
  "rotation": 0,
  "sharedStyleID": "EF6B8C4B-9B6F-4937-904E-63C0AAED3FF3",
  "shouldBreakMaskChain": false,
  "style": {
    "_class": "style",
    "do_objectID": "D16798AE-0875-4040-8238-1B8E24749FC3",
    "endMarkerType": 0,
    "miterLimit": 10,
    "startMarkerType": 0,
    "textStyle": {
      "_class": "textStyle",
      "do_objectID": "070EA974-5DAB-4ECB-AC3F-414B2E566252",
      "encodedAttributes": {
        "MSAttributedStringColorAttribute": {
          "_class": "color",
          "alpha": 1,
          "blue": 0.3882352941,
          "green": 0.3882352941,
          "red": 0.3882352941
        },
        "MSAttributedStringFontAttribute": {
          "_class": "fontDescriptor",
          "attributes": {
            "name": "SFUIText-Regular",
            "size": 12
          }
        },
        "paragraphStyle": {
          "_class": "paragraphStyle",
          "alignment": 0,
          "allowsDefaultTighteningForTruncation": 0
        }
      },
      "verticalAlignment": 0
    },
    "windingRule": 1
  },
  "textBehaviour": 1
}