{
  "_class": "shapeGroup",
  "booleanOperation": 0,
  "clippingMaskMode": 0,
  "do_objectID": "25C688E3-7460-450C-ADE3-01D2544519B5",
  "exportOptions": {
    "_class": "exportOptions",
    "do_objectID": "87DB0DD2-C0D0-4EA8-B380-35E271F9442F",
    "exportFormats": [
    ],
    "includedLayerIds": [
    ],
    "layerOptions": 0,
    "shouldTrim": false
  },
  "frame": {
    "_class": "rect",
    "constrainProportions": true,
    "do_objectID": "8B52FE10-0982-4BA0-B803-78FD73B075A5",
    "height": 75.06561679790029,
    "width": 75.00000000000001,
    "x": 0,
    "y": 0.1093613298339733
  },
  "hasClickThrough": false,
  "hasClippingMask": false,
  "isFixedToViewport": false,
  "isFlippedHorizontal": false,
  "isFlippedVertical": false,
  "isLocked": false,
  "isVisible": true,
  "layerListExpandedType": 0,
  "layers": [
    {
      "class": "oval",
      "id": "ED32DD4A-D174-4C50-BD31-C8ED5143AEE5"
    }
  ],
  "name": "Color",
  "nameIsFixed": true,
  "resizingConstraint": 63,
  "resizingType": 0,
  "rotation": 0,
  "shouldBreakMaskChain": false,
  "style": {
    "_class": "style",
    "blur": {
      "_class": "blur",
      "center": "{0.5, 0.5}",
      "do_objectID": "E1597DEC-D0B8-43D0-ACFC-6A39DA51A1F5",
      "isEnabled": false,
      "motionAngle": 0,
      "radius": 5,
      "type": 0
    },
    "do_objectID": "7B8E6851-4246-4204-AAA5-0D07439F17C2",
    "endMarkerType": 0,
    "fills": [
      {
        "_class": "fill",
        "color": {
          "_class": "color",
          "alpha": 1,
          "blue": 0.9019607843137255,
          "green": 0.9019607843137255,
          "red": 0.9019607843137255
        },
        "fillType": 0,
        "isEnabled": true,
        "noiseIndex": 0,
        "noiseIntensity": 0,
        "patternFillType": 0,
        "patternTileScale": 1
      }
    ],
    "miterLimit": 10,
    "startMarkerType": 0,
    "windingRule": 1
  },
  "windingRule": 1
}