{
  "_class": "symbolInstance",
  "booleanOperation": 0,
  "do_objectID": "5C3D3FBF-066C-414E-A448-19C46806642C",
  "exportOptions": {
    "_class": "exportOptions",
    "do_objectID": "1A9A3562-E9DE-4CE1-89EA-1C59078B8C0F",
    "exportFormats": [
    ],
    "includedLayerIds": [
    ],
    "layerOptions": 0,
    "shouldTrim": false
  },
  "frame": {
    "_class": "rect",
    "constrainProportions": false,
    "do_objectID": "5E8C7E50-6351-4912-92B1-A18ADF71A41F",
    "height": 253,
    "width": 375,
    "x": 1050,
    "y": 3772
  },
  "horizontalSpacing": 0,
  "isFixedToViewport": false,
  "isFlippedHorizontal": false,
  "isFlippedVertical": false,
  "isLocked": false,
  "isVisible": true,
  "layerListExpandedType": 0,
  "name": "Timeline / Weibo / 375 / Small Page / 1+2",
  "nameIsFixed": false,
  "overrideValues": [
  ],
  "resizingConstraint": 63,
  "resizingType": 0,
  "rotation": 0,
  "scale": 1,
  "shouldBreakMaskChain": false,
  "style": {
    "_class": "style",
    "do_objectID": "F28BEB40-962B-4654-87C5-EA60ABB3FA7B",
    "endMarkerType": 0,
    "miterLimit": 10,
    "startMarkerType": 0,
    "windingRule": 1
  },
  "symbolID": "2E76EB7C-9337-44B5-B83F-EBECEFAF09AF",
  "verticalSpacing": 0
}