{
  "_class": "shapePath",
  "booleanOperation": -1,
  "clippingMaskMode": 0,
  "do_objectID": "A5A6F023-363C-450E-A632-2E98E1665A08",
  "edited": true,
  "exportOptions": {
    "_class": "exportOptions",
    "do_objectID": "E4B8F8D3-6AEB-48CC-80FD-BD80BDE05B09",
    "exportFormats": [
    ],
    "includedLayerIds": [
    ],
    "layerOptions": 0,
    "shouldTrim": false
  },
  "frame": {
    "_class": "rect",
    "constrainProportions": false,
    "do_objectID": "A1CA19CB-49D8-43A0-86EC-E3289D6992AE",
    "height": 1,
    "width": 3,
    "x": 10.54785625918885,
    "y": 8.977039291819892
  },
  "hasClippingMask": false,
  "isClosed": false,
  "isFixedToViewport": false,
  "isFlippedHorizontal": false,
  "isFlippedVertical": false,
  "isLocked": false,
  "isVisible": true,
  "layerListExpandedType": 0,
  "name": "Line",
  "nameIsFixed": false,
  "pointRadiusBehaviour": 1,
  "points": [
    {
      "_class": "curvePoint",
      "cornerRadius": 0,
      "curveFrom": "{0.22222222222222182, 0.25}",
      "curveMode": 1,
      "curveTo": "{0.16666666666666619, 0.75}",
      "hasCurveFrom": false,
      "hasCurveTo": false,
      "point": "{-4.5796699765787707e-16, 0.25}"
    },
    {
      "_class": "curvePoint",
      "cornerRadius": 0,
      "curveFrom": "{0.72222222222222154, 0}",
      "curveMode": 2,
      "curveTo": "{0.27777777777777746, 0}",
      "hasCurveFrom": true,
      "hasCurveTo": true,
      "point": "{0.49999999999999956, 0}"
    },
    {
      "_class": "curvePoint",
      "cornerRadius": 0,
      "curveFrom": "{0.16666666666666619, 1.7499999999999991}",
      "curveMode": 1,
      "curveTo": "{0.77777777777777746, 0.25}",
      "hasCurveFrom": false,
      "hasCurveTo": false,
      "point": "{0.99999999999999956, 0.25}"
    }
  ],
  "resizingConstraint": 63,
  "resizingType": 0,
  "rotation": 11,
  "shouldBreakMaskChain": false,
  "style": {
    "_class": "style",
    "borderOptions": {
      "_class": "borderOptions",
      "dashPattern": [
      ],
      "do_objectID": "59D85455-0759-40E5-9716-750941546778",
      "isEnabled": false,
      "lineCapStyle": 1,
      "lineJoinStyle": 0
    },
    "borders": [
      {
        "_class": "border",
        "color": {
          "_class": "color",
          "alpha": 1,
          "blue": 0.3882352941176471,
          "green": 0.3882352941176471,
          "red": 0.3882352941176471
        },
        "fillType": 0,
        "isEnabled": true,
        "position": 0,
        "thickness": 1
      }
    ],
    "do_objectID": "C4DDA652-FBDF-4753-841F-DE4ED4F294CD",
    "endMarkerType": 0,
    "fills": [
      {
        "_class": "fill",
        "color": {
          "_class": "color",
          "alpha": 1,
          "blue": 0.847,
          "green": 0.847,
          "red": 0.847
        },
        "fillType": 0,
        "isEnabled": false,
        "noiseIndex": 0,
        "noiseIntensity": 0,
        "patternFillType": 1,
        "patternTileScale": 1
      }
    ],
    "miterLimit": 10,
    "startMarkerType": 0,
    "windingRule": 1
  }
}