{
  "_class": "group",
  "booleanOperation": 0,
  "clippingMaskMode": 0,
  "do_objectID": "B29BBC34-9805-41FD-B275-2C35D28082C9",
  "exportOptions": {
    "_class": "exportOptions",
    "do_objectID": "51F00866-A45D-4AFB-B358-8620D2DBA76B",
    "exportFormats": [
    ],
    "includedLayerIds": [
    ],
    "layerOptions": 0,
    "shouldTrim": false
  },
  "frame": {
    "_class": "rect",
    "constrainProportions": false,
    "do_objectID": "BDBFF40B-8374-4A0B-B324-609406355EA6",
    "height": 388,
    "width": 414,
    "x": 0,
    "y": 0
  },
  "groupLayout": {
    "_class": "MSImmutableFreeformGroupLayout",
    "do_objectID": "9E89F7C4-CA1E-463E-A049-B920AE8EBF76"
  },
  "hasClickThrough": false,
  "hasClippingMask": false,
  "isFixedToViewport": false,
  "isFlippedHorizontal": false,
  "isFlippedVertical": false,
  "isLocked": false,
  "isVisible": true,
  "layerListExpandedType": 2,
  "layers": [
    {
      "class": "symbolInstance",
      "id": "DD23BD3D-2120-46A1-A69B-214B1C60F367"
    },
    {
      "class": "symbolInstance",
      "id": "ADBD8647-6BD7-4CE2-BCF6-D1F29500CEEB"
    },
    {
      "class": "group",
      "id": "C466177C-87F5-4936-9437-2754BC76F5EF"
    },
    {
      "class": "symbolInstance",
      "id": "C1B9B499-F32F-4B75-897D-644048E26110"
    },
    {
      "class": "text",
      "id": "BF16BF3D-7010-4CE2-8543-1D74B24BAB3C"
    },
    {
      "class": "symbolInstance",
      "id": "C64D489A-3B9E-4B76-A69F-64B769D75110"
    },
    {
      "class": "group",
      "id": "5C28B2AF-45FD-425B-B51C-F589D1CA7C50"
    }
  ],
  "name": "Timeline / Weibo / 375 / Small Page / AD Pic",
  "nameIsFixed": true,
  "resizingConstraint": 63,
  "resizingType": 0,
  "rotation": 0,
  "shouldBreakMaskChain": false,
  "style": {
    "_class": "style",
    "do_objectID": "33509650-B3C3-4426-B318-5970B356D90D",
    "endMarkerType": 0,
    "miterLimit": 10,
    "startMarkerType": 0,
    "windingRule": 1
  }
}