{
  "_class": "symbolMaster",
  "backgroundColor": {
    "_class": "color",
    "alpha": 1,
    "blue": 1,
    "do_objectID": "8E30E365-9B17-4705-9993-B5B9FB6D74B3",
    "green": 1,
    "red": 1
  },
  "booleanOperation": 0,
  "changeIdentifier": 2,
  "do_objectID": "4A10F368-2925-46BF-B654-8ADD0CB534EB",
  "exportOptions": {
    "_class": "exportOptions",
    "do_objectID": "0EC37DCB-64A4-42B3-A5A1-76EEC79702D3",
    "exportFormats": [
    ],
    "includedLayerIds": [
    ],
    "layerOptions": 0,
    "shouldTrim": false
  },
  "frame": {
    "_class": "rect",
    "constrainProportions": false,
    "do_objectID": "00D52561-7A80-478A-BDB2-B1DAC6BB052E",
    "height": 20,
    "width": 50,
    "x": 66,
    "y": 6712
  },
  "hasBackgroundColor": false,
  "hasClickThrough": true,
  "horizontalRulerData": {
    "_class": "rulerData",
    "base": 0,
    "do_objectID": "24F7037F-D636-46CB-A654-9C4370A4EBFF",
    "guides": [
    ]
  },
  "includeBackgroundColorInExport": true,
  "includeBackgroundColorInInstance": false,
  "includeInCloudUpload": true,
  "isFixedToViewport": false,
  "isFlippedHorizontal": false,
  "isFlippedVertical": false,
  "isFlowHome": false,
  "isLocked": false,
  "isVisible": true,
  "layerListExpandedType": 1,
  "layers": [
    {
      "class": "shapeGroup",
      "id": "FF425987-995C-45E3-9A15-ED79F83CDD85"
    },
    {
      "class": "text",
      "id": "A0CF4818-4098-4223-ACD7-0524C3C69892"
    }
  ],
  "name": "Common / Button / Super Small / Green / Highlighted",
  "nameIsFixed": true,
  "resizesContent": false,
  "resizingConstraint": 63,
  "resizingType": 0,
  "rotation": 0,
  "shouldBreakMaskChain": true,
  "style": {
    "_class": "style",
    "do_objectID": "3CDB457F-44A0-4A75-814F-21CC0F8C8A5D",
    "endMarkerType": 0,
    "miterLimit": 10,
    "startMarkerType": 0,
    "windingRule": 1
  },
  "symbolID": "9249C4A0-2E8A-4D07-87A4-B74C91C53918",
  "userInfo": {
    "com.animaapp.stc-sketch-plugin": {
      "kModelPropertiesKey": {
      }
    }
  },
  "verticalRulerData": {
    "_class": "rulerData",
    "base": 0,
    "do_objectID": "8B63816C-38A2-4695-8CFE-E9F42B7F11F4",
    "guides": [
    ]
  }
}