{
  "_class": "group",
  "booleanOperation": 0,
  "clippingMaskMode": 0,
  "do_objectID": "B24A896B-C3B7-4837-A1FF-30EA8638224B",
  "exportOptions": {
    "_class": "exportOptions",
    "do_objectID": "9EAD4E9D-6616-415B-A431-82D9BD67684A",
    "exportFormats": [
    ],
    "includedLayerIds": [
    ],
    "layerOptions": 0,
    "shouldTrim": false
  },
  "frame": {
    "_class": "rect",
    "constrainProportions": false,
    "do_objectID": "156731F4-805A-47BA-BD11-01101C1BB93F",
    "height": 126,
    "width": 256,
    "x": 14,
    "y": 255
  },
  "groupLayout": {
    "_class": "MSImmutableFreeformGroupLayout",
    "do_objectID": "15DC38F4-7CE0-400E-B728-73573D45E2BE"
  },
  "hasClickThrough": false,
  "hasClippingMask": false,
  "isFixedToViewport": false,
  "isFlippedHorizontal": false,
  "isFlippedVertical": false,
  "isLocked": false,
  "isVisible": true,
  "layerListExpandedType": 2,
  "layers": [
    {
      "class": "rectangle",
      "id": "74678499-F2D8-4062-976E-5BF6B848E864"
    },
    {
      "class": "rectangle",
      "id": "990B5F37-228A-4491-AECE-95D774691461"
    }
  ],
  "name": "Timeline  / 9 Picture ",
  "nameIsFixed": true,
  "resizingConstraint": 63,
  "resizingType": 0,
  "rotation": 0,
  "shouldBreakMaskChain": false,
  "style": {
    "_class": "style",
    "do_objectID": "B2603CC4-5E58-46DF-AB0B-535CDFE41C15",
    "endMarkerType": 0,
    "miterLimit": 10,
    "startMarkerType": 0,
    "windingRule": 1
  }
}