{
  "_class": "symbolMaster",
  "backgroundColor": {
    "_class": "color",
    "alpha": 1,
    "blue": 1,
    "do_objectID": "AFE66885-4E1D-49EB-AB8F-9A7E289B7322",
    "green": 1,
    "red": 1
  },
  "booleanOperation": 0,
  "changeIdentifier": 1,
  "clippingMaskMode": 0,
  "do_objectID": "7BD0BED3-65F0-468D-9F64-273394E7BEF5",
  "exportOptions": {
    "_class": "exportOptions",
    "do_objectID": "534FEA79-98AA-454A-92EF-B2EE3260A72C",
    "exportFormats": [
    ],
    "includedLayerIds": [
    ],
    "layerOptions": 0,
    "shouldTrim": false
  },
  "frame": {
    "_class": "rect",
    "constrainProportions": false,
    "do_objectID": "3CE6946F-AADB-473A-813D-275E37AF518B",
    "height": 42,
    "width": 272,
    "x": -436,
    "y": 6209
  },
  "hasBackgroundColor": false,
  "hasClickThrough": true,
  "hasClippingMask": false,
  "horizontalRulerData": {
    "_class": "rulerData",
    "base": 0,
    "do_objectID": "22242B10-C0E2-43E4-B2C5-E25A50F19C01",
    "guides": [
    ]
  },
  "includeBackgroundColorInExport": true,
  "includeBackgroundColorInInstance": false,
  "includeInCloudUpload": true,
  "isFixedToViewport": false,
  "isFlippedHorizontal": false,
  "isFlippedVertical": false,
  "isFlowHome": false,
  "isLocked": false,
  "isVisible": true,
  "layerListExpandedType": 1,
  "layers": [
    {
      "class": "rectangle",
      "id": "F8342A8D-1D31-4BEA-9E73-DC8E8C14AE4A"
    },
    {
      "class": "text",
      "id": "D58BCE07-A235-4FF6-872E-DDBE44062CBA"
    }
  ],
  "name": "Common / Button / Big / Orange / Normal",
  "nameIsFixed": true,
  "resizesContent": false,
  "resizingConstraint": 63,
  "resizingType": 0,
  "rotation": 0,
  "shouldBreakMaskChain": true,
  "style": {
    "_class": "style",
    "do_objectID": "64EA3633-F96C-4F91-8992-045DFBCFDD93",
    "endMarkerType": 0,
    "miterLimit": 10,
    "startMarkerType": 0,
    "windingRule": 1
  },
  "symbolID": "BE348723-7930-4307-98C0-83DDD86610A9",
  "verticalRulerData": {
    "_class": "rulerData",
    "base": 0,
    "do_objectID": "D982FE84-999E-401E-B136-24C2DD2CCF21",
    "guides": [
    ]
  }
}